{"assets":{"98B1518084AFD5A94610132E6B499B27":{"type":"texture","index":0,"assetRequest":{"type":"slide","state":"contents","slide":"none"},"url":{"native":"assets\/042DDCAD-43BA-4164-9D7F-57530831340F.pdf"},"width":1920,"height":1080},"F128EDC3CBA4FB73DBD180C2F06DBEAC":{"type":"texture","index":1,"assetRequest":{"type":"slide","state":"contents","slide":"none"},"url":{"native":"assets\/042DDCAD-43BA-4164-9D7F-57530831340F.pdf"},"width":1920,"height":1080}},"events":[{"effects":[{"beginTime":0,"baseLayer":{"animations":[],"initialState":{"affineTransform":[1,0,0,1,0,0],"masksToBounds":false,"rotation":0,"scale":1,"position":{"pointX":960,"pointY":540},"width":1920,"sublayerTransform":[1,0,0,0,0,1,0,0,0,0,1,0,0,0,0,1],"contentsRect":{"y":0,"x":0,"width":1,"height":1},"opacity":1,"edgeAntialiasingMask":251658240,"height":1080,"hidden":false,"anchorPoint":{"pointX":0.5,"pointY":0.5}},"objectID":"0","layers":[{"animations":[],"initialState":{"affineTransform":[1,0,0,1,0,0],"masksToBounds":false,"rotation":0,"scale":1,"position":{"pointX":960,"pointY":540},"width":1920,"sublayerTransform":[1,0,0,0,0,1,0,0,0,0,1,-0.00035007912466775983,0,0,0,1],"contentsRect":{"y":0,"x":0,"width":1,"height":1},"opacity":1,"edgeAntialiasingMask":251658240,"height":1080,"hidden":false,"anchorPoint":{"pointX":0.5,"pointY":0.5}},"layers":[{"animations":[],"layers":[],"texturedRectangle":{"isBackgroundTexture":false,"singleTextureOpacity":1,"textureType":0,"textBaseline":0,"textXHeight":0,"isVerticalText":false},"initialState":{"affineTransform":[1,0,0,1,0,0],"masksToBounds":false,"rotation":0,"scale":1,"position":{"pointX":960,"pointY":540},"width":1920,"sublayerTransform":[1,0,0,0,0,1,0,0,0,0,1,0,0,0,0,1],"contentsRect":{"y":0,"x":0,"width":1,"height":1},"opacity":1,"edgeAntialiasingMask":0,"height":1080,"hidden":false,"anchorPoint":{"pointX":0.5,"pointY":0.5}},"texture":"F128EDC3CBA4FB73DBD180C2F06DBEAC"},{"animations":[{"additive":false,"timeOffset":0,"beginTime":0,"from":{"scalar":false},"repeatCount":0,"fillMode":"both","duration":0.01,"autoreverses":false,"property":"hidden","to":{"scalar":true},"removedOnCompletion":false}],"layers":[],"texturedRectangle":{"isBackgroundTexture":false,"singleTextureOpacity":1,"textureType":0,"textBaseline":0,"textXHeight":0,"isVerticalText":false},"initialState":{"affineTransform":[1,0,0,1,0,0],"masksToBounds":false,"rotation":0,"scale":1,"position":{"pointX":960,"pointY":540},"width":1920,"sublayerTransform":[1,0,0,0,0,1,0,0,0,0,1,0,0,0,0,1],"contentsRect":{"y":0,"x":0,"width":1,"height":1},"opacity":1,"edgeAntialiasingMask":0,"height":1080,"hidden":false,"anchorPoint":{"pointX":0.5,"pointY":0.5}},"texture":"98B1518084AFD5A94610132E6B499B27"}]}]},"effects":[],"duration":0.01,"type":"transition","attributes":{"direction":0},"name":"none","objectID":"0"}],"automaticPlay":false,"hyperlinks":[],"accessibility":[{"text":"Test\\u2028Site","targetRectangle":{"y":406.86267709732056,"x":947.47001719474792,"width":36.700000000000045,"height":52.20000034570694}},{"text":"Short-from","targetRectangle":{"y":516.24609303474426,"x":1229.3956775665283,"width":168.59999999999991,"height":58}},{"text":"Contents","targetRectangle":{"y":562.64609372615814,"x":1241.7356775665282,"width":143.92000000000007,"height":58}},{"text":"Video \\u2028Content","targetRectangle":{"y":542.34610605239868,"x":1062.7427504062653,"width":69.809999999999945,"height":52.20000034570694}},{"text":"AI","targetRectangle":{"y":834.39231741428375,"x":942.90002995729446,"width":34.200000000000045,"height":58}},{"text":"Vispot Service","targetRectangle":{"y":244.49986135959625,"x":841.18003511428833,"width":237.63999999999987,"height":58}},{"text":"Human \\u2028Resources","targetRectangle":{"y":683.82437753677368,"x":920.4000164270401,"width":83.980000000000018,"height":52.20000034570694}},{"text":"Brand Identity","targetRectangle":{"y":112.70440673828125,"x":848.41999999999996,"width":223.15999999999997,"height":58}},{"text":"CORE\\u2028IDENTITY","targetRectangle":{"y":531.54608976840973,"x":905.96003198623657,"width":108.08000000000004,"height":73.800000488758087}},{"text":"Fashion ","targetRectangle":{"y":542.34610605239868,"x":799.83967733383179,"width":68.159999999999968,"height":29}},{"text":"CEO","targetRectangle":{"y":565.54610639810562,"x":810.88967733383174,"width":40.060000000000059,"height":29}},{"text":"B2B를 넘어 B2C고객까지 AI로 만든 숏폼콘텐츠를 비스팟을 통하여 제공한다.","targetRectangle":{"y":938.39910805225372,"x":354.55999565124512,"width":1210.8800000000001,"height":59}},{"text":"All","targetRectangle":{"y":516.24609303474426,"x":590.70441237449643,"width":42.240000000000009,"height":58}},{"text":"Customer","targetRectangle":{"y":562.64609372615814,"x":533.04441237449646,"width":157.55999999999995,"height":58}}],"baseLayer":{"animations":[],"initialState":{"affineTransform":[1,0,0,1,0,0],"masksToBounds":false,"rotation":0,"scale":1,"position":{"pointX":960,"pointY":540},"width":1920,"sublayerTransform":[1,0,0,0,0,1,0,0,0,0,1,0,0,0,0,1],"contentsRect":{"y":0,"x":0,"width":1,"height":1},"opacity":1,"edgeAntialiasingMask":251658240,"height":1080,"hidden":false,"anchorPoint":{"pointX":0.5,"pointY":0.5}},"objectID":"0","layers":[{"animations":[],"initialState":{"affineTransform":[1,0,0,1,0,0],"masksToBounds":false,"rotation":0,"scale":1,"position":{"pointX":960,"pointY":540},"width":1920,"sublayerTransform":[1,0,0,0,0,1,0,0,0,0,1,-0.00035007912466775983,0,0,0,1],"contentsRect":{"y":0,"x":0,"width":1,"height":1},"opacity":1,"edgeAntialiasingMask":251658240,"height":1080,"hidden":false,"anchorPoint":{"pointX":0.5,"pointY":0.5}},"layers":[{"animations":[],"layers":[],"texturedRectangle":{"isBackgroundTexture":false,"singleTextureOpacity":1,"textureType":0,"textBaseline":0,"textXHeight":0,"isVerticalText":false},"initialState":{"affineTransform":[1,0,0,1,0,0],"masksToBounds":false,"rotation":0,"scale":1,"position":{"pointX":960,"pointY":540},"width":1920,"sublayerTransform":[1,0,0,0,0,1,0,0,0,0,1,0,0,0,0,1],"contentsRect":{"y":0,"x":0,"width":1,"height":1},"opacity":1,"edgeAntialiasingMask":0,"height":1080,"hidden":false,"anchorPoint":{"pointX":0.5,"pointY":0.5}},"texture":"98B1518084AFD5A94610132E6B499B27"}]}]}}]}